cosapp/__init__.py
cosapp/base/__init__.py
cosapp/core/__init__.py
cosapp/core/_version.py
cosapp/core/config.py
cosapp/core/configuration_schema.json
cosapp/core/eval_str.py
cosapp/core/module.py
cosapp/core/time.py
cosapp/core/variableref.py
cosapp/core/execution/__init__.py
cosapp/core/execution/comms.py
cosapp/core/execution/context.py
cosapp/core/execution/ops.py
cosapp/core/execution/pool.py
cosapp/core/execution/task.py
cosapp/core/execution/worker.py
cosapp/core/numerics/__init__.py
cosapp/core/numerics/basics.py
cosapp/core/numerics/boundary.py
cosapp/core/numerics/enum.py
cosapp/core/numerics/mathematicalproblem.schema.json
cosapp/core/numerics/residues.py
cosapp/core/numerics/utils.py
cosapp/core/numerics/solve/__init__.py
cosapp/core/numerics/solve/jacobian.py
cosapp/core/numerics/solve/linear_solver.py
cosapp/core/numerics/solve/non_linear_solver.py
cosapp/core/numerics/solve/root.py
cosapp/core/signal/__init__.py
cosapp/core/signal/signal.py
cosapp/core/signal/slot.py
cosapp/core/tests/__init__.py
cosapp/core/tests/conftest.py
cosapp/core/tests/test_AssignString.py
cosapp/core/tests/test_CoSAppConfiguration.py
cosapp/core/tests/test_EvalString.py
cosapp/core/tests/test_Module.py
cosapp/core/tests/test_time.py
cosapp/drivers/__init__.py
cosapp/drivers/abstractsetofcases.py
cosapp/drivers/abstractsolver.py
cosapp/drivers/driver.py
cosapp/drivers/fixedpoint.py
cosapp/drivers/influence.py
cosapp/drivers/iterativecase.py
cosapp/drivers/lineardoe.py
cosapp/drivers/metasystembuilder.py
cosapp/drivers/montecarlo.py
cosapp/drivers/nonlinearsolver.py
cosapp/drivers/optimizer.py
cosapp/drivers/optionaldriver.py
cosapp/drivers/runonce.py
cosapp/drivers/runsinglecase.py
cosapp/drivers/utils.py
cosapp/drivers/validitycheck.py
cosapp/drivers/time/__init__.py
cosapp/drivers/time/base.py
cosapp/drivers/time/bdf.py
cosapp/drivers/time/crank_nicolson.py
cosapp/drivers/time/euler.py
cosapp/drivers/time/implicit.py
cosapp/drivers/time/runge_kutta.py
cosapp-1.4.0.dist-info/licenses/LICENSE.rst
cosapp-1.4.0.dist-info/METADATA
cosapp-1.4.0.dist-info/WHEEL
cosapp-1.4.0.dist-info/top_level.txt
cosapp-1.4.0.dist-info/RECORD
