Metadata-Version: 2.4
Name: cosapp
Version: 1.4.0
Summary: CoSApp, the Collaborative System Approach.
Home-page: https://cosapp.readthedocs.io
Author: CoSApp Development Team
License: Apache-2.0
Keywords: cosapp,system simulation,system design
Classifier: Development Status :: 3 - Alpha
Classifier: Intended Audience :: End Users/Desktop
Classifier: Intended Audience :: Developers
Classifier: Intended Audience :: Science/Research
Classifier: License :: OSI Approved :: Apache Software License
Classifier: Natural Language :: English
Classifier: Programming Language :: Python :: 3
Classifier: Programming Language :: Python :: 3.9
Classifier: Programming Language :: Python :: 3.10
Classifier: Programming Language :: Python :: 3.11
Requires-Python: >=3.9
License-File: LICENSE.rst
Requires-Dist: pandas
Requires-Dist: jsonschema
Requires-Dist: numpy>1.12
Requires-Dist: scipy
Requires-Dist: jinja2
Provides-Extra: extra
Requires-Dist: ipython; extra == "extra"
Requires-Dist: pythonfmu; extra == "extra"
Requires-Dist: watchdog; extra == "extra"
Provides-Extra: tests
Requires-Dist: coverage; extra == "tests"
Requires-Dist: pytest; extra == "tests"
Requires-Dist: pyfmi; extra == "tests"
Provides-Extra: docs
Requires-Dist: sphinx; extra == "docs"
Requires-Dist: nbsphinx>=0.6.0; extra == "docs"
Requires-Dist: sphinx-copybutton; extra == "docs"
Requires-Dist: sphinx-mdinclude; extra == "docs"
Requires-Dist: jupyter_client; extra == "docs"
Requires-Dist: ipykernel; extra == "docs"
Requires-Dist: ipywidgets; extra == "docs"
Requires-Dist: plotly; extra == "docs"
Requires-Dist: pyfmi; extra == "docs"
Requires-Dist: pytest; extra == "docs"
Dynamic: license-file
